{
    "network": "10716_weakly_connected_10",
    "model_type": "pdgrapher",
    "metrics": {
        "accuracy": 0.011,
        "avg rank of source": 2527.892,
        "avg prediction for source": 0.515,
        "avg prediction over all nodes": -0.3,
        "min prediction over all nodes": -2.883,
        "max prediction over all nodes": 8.316,
        "source in top 5": 0.032,
        "source in top 20": 0.051,
        "source in top 40": 0.068,
        "source in top 80": 0.088
    },
    "parameters": {
        "data_creation": {
            "n_samples": 20000,
            "time_steps": null,
            "training_share": 0.6,
            "normalize_data": true,
            "network": "10716_weakly_connected_10",
            "remove_near_duplicates": false
        },
        "graph_perturbation": {
            "random_graph": false,
            "self_loop_graph": false,
            "noise": {
                "missing_edges": 0,
                "wrong_edges": 0
            }
        },
        "on_cluster": true,
        "seed": 42,
        "gene_specific_metrics": {
            "enabled": false,
            "genes_of_interest": []
        },
        "data_path": "data",
        "model_path": "models",
        "figures_path": "figures",
        "report_path": "reports",
        "topo_path": "topos",
        "model": "PDGrapher",
        "model_name": "pdgrapher_default",
        "training": {
            "epochs": 200,
            "layers": 3,
            "alpha": 0.75,
            "batch_size": 1,
            "class_weighting": true,
            "graph_weighting": true,
            "hidden_size": 256,
            "heads": 8,
            "dropout": 0.1,
            "learning_rate": 0.0002,
            "subsample": false,
            "weight_decay": 0.0001
        },
        "experiment": "10716_weakly_connected_10"
    }
}