{
    "network": "barabasi_64",
    "model_type": "pdgraphernognn",
    "metrics": {
        "accuracy": 0.045,
        "avg rank of source": 27.281,
        "avg prediction for source": -1.278,
        "avg prediction over all nodes": -1.721,
        "min prediction over all nodes": -6.019,
        "max prediction over all nodes": 6.026,
        "source in top 5": 0.148,
        "source in top 20": 0.418,
        "source in top 40": 0.689,
        "source in top 80": 1.0,
        "pdgrapher_perturbation_discovery": {
            "recall@1": 0.0162,
            "recall@10": 0.1463,
            "recall@100": 1.0,
            "recall@1000": 1.0,
            "ranking_score": 0.5004,
            "ranking_score_dcg": 0.1411,
            "perc_partially_accurate_predictions": 1.62,
            "recall@1_std": 0.1261,
            "recall@10_std": 0.3534,
            "recall@100_std": 0.0,
            "recall@1000_std": 0.0,
            "ranking_score_std": 0.285,
            "ranking_score_dcg_std": 0.1623,
            "perc_partially_accurate_predictions_std": 12.61,
            "total_samples": 1114,
            "avg_topk": 32.0233
        },
        "pdgrapher_response_prediction": {
            "forward_mae": -1,
            "forward_mse": -1,
            "forward_r2": -1,
            "forward_r2_scgen": -1,
            "forward_spearman": -1,
            "backward_mae": -1,
            "backward_mse": -1,
            "backward_r2": -1,
            "backward_r2_scgen": -1,
            "backward_spearman": -1,
            "backward_avg_topk": -1
        }
    },
    "parameters": {
        "data_creation": {
            "n_samples": 5000,
            "time_steps": null,
            "training_share": 0.6,
            "normalize_data": true,
            "network": "barabasi_64",
            "remove_near_duplicates": false
        },
        "graph_perturbation": {
            "random_graph": false,
            "self_loop_graph": false,
            "noise": {
                "missing_edges": 0,
                "wrong_edges": 0
            }
        },
        "on_cluster": true,
        "seed": 42,
        "gene_specific_metrics": {
            "enabled": true,
            "genes_of_interest": [
                "IRF3",
                "ATF7",
                "SREBF2",
                "MYC"
            ]
        },
        "data_path": "data",
        "model_path": "models",
        "figures_path": "figures",
        "report_path": "reports",
        "topo_path": "topos",
        "model": "PDGrapherNoGNN",
        "model_name": "pdgrapher_nognn_default",
        "training": {
            "epochs": 100,
            "layers": 3,
            "alpha": 0.75,
            "batch_size": 8,
            "class_weighting": true,
            "graph_weighting": true,
            "hidden_size": 256,
            "heads": 8,
            "dropout": 0.1,
            "learning_rate": 0.0002,
            "subsample": false,
            "weight_decay": 0.0001
        },
        "experiment": "small_graph"
    },
    "data stats": {
        "graph stats": {
            "number of nodes": 64,
            "number of possible sources": 64
        },
        "infection stats": {
            "avg number of sources": 1.0,
            "avg portion of affected nodes": 0.983,
            "std portion of affected nodes": 0.102
        }
    }
}